rosenbrock/__init__.py
rosenbrock/rosenbrock.py
rosenbrock-0.7.1.dist-info/LICENSE
rosenbrock-0.7.1.dist-info/METADATA
rosenbrock-0.7.1.dist-info/WHEEL
rosenbrock-0.7.1.dist-info/top_level.txt
rosenbrock-0.7.1.dist-info/RECORD
