Metadata-Version: 2.1
Name: rosenbrock
Version: 0.7.1
Summary: Rosenbrock distribution, including unnormalized density and analytic sampler
Home-page: https://github.com/alisiahkoohi/rosenbrock
Author: Ali Siahkoohi
Author-email: ali.siahkoohi@gmail.com
License: UNKNOWN
Platform: UNKNOWN
Classifier: Programming Language :: Python :: 3
Classifier: License :: OSI Approved :: MIT License
Classifier: Operating System :: OS Independent
Requires-Python: >=3.6
License-File: LICENSE
Requires-Dist: torch
